hatch_paulrein_template/__about__.py
hatch_paulrein_template/__init__.py
hatch_paulrein_template/file_templates.py
hatch_paulrein_template/hooks.py
hatch_paulrein_template/plugin.py
hatch_paulrein_template-1.0.2.dist-info/METADATA
hatch_paulrein_template-1.0.2.dist-info/WHEEL
hatch_paulrein_template-1.0.2.dist-info/entry_points.txt
hatch_paulrein_template-1.0.2.dist-info/licenses/LICENSE.txt
hatch_paulrein_template-1.0.2.dist-info/RECORD
