Metadata-Version: 2.3
Name: hatch-paulrein-template
Version: 1.0.2
Summary: A hatch plugin to create a better project template.
Project-URL: Documentation, https://github.com/Paul Reinerfelt/hatch-paulrein-template#readme
Project-URL: Issues, https://github.com/Paul Reinerfelt/hatch-paulrein-template/issues
Project-URL: Source, https://github.com/Paul Reinerfelt/hatch-paulrein-template
Author-email: Paul Reinerfelt <Paul.Reinerfelt@gmail.com>
License-Expression: MIT
License-File: LICENSE.txt
Classifier: Development Status :: 4 - Beta
Classifier: Framework :: Hatch
Classifier: Programming Language :: Python
Classifier: Programming Language :: Python :: 3.8
Classifier: Programming Language :: Python :: 3.9
Classifier: Programming Language :: Python :: 3.10
Classifier: Programming Language :: Python :: 3.11
Classifier: Programming Language :: Python :: 3.12
Classifier: Programming Language :: Python :: Implementation :: CPython
Classifier: Programming Language :: Python :: Implementation :: PyPy
Requires-Python: >=3.8
Requires-Dist: hatch
